{
  "metadata": {
    "description": "PodcastIQ curated channel list — 25 channels across 6 genres",
    "target_episodes_total": 250,
    "default_episodes_per_channel": 10,
    "date_range": "2022-01-01 to 2026-02-20",
    "min_duration_minutes": 30,
    "max_duration_minutes": 240
  },
  "channels": [
    {
      "channel_id": "UCSHZKyawb77ixDdsGog4iWA",
      "name": "Lex Fridman Podcast",
      "handle": "@lexfridman",
      "genre": "Technology & AI",
      "target_episodes": 10,
      "notes": "Focus on AI/tech guests, skip history/philosophy-only eps"
    },
    {
      "channel_id": "UCESLZhusAkFfsNsApnjF_Cg",
      "name": "All-In Podcast",
      "handle": "@allin",
      "genre": "Technology & AI",
      "target_episodes": 10,
      "notes": "4 speakers — great for multi-speaker testing"
    },
    {
      "channel_id": "UCSI7h9hydQ40K5MJHnCrQvw",
      "name": "No Priors",
      "handle": "@NoPriorsPodcast",
      "genre": "Technology & AI",
      "target_episodes": 10,
      "notes": "Shorter episodes, AI/startup focused"
    },
    {
      "channel_id": "UCyFqFYfTW2VoIQKylJ04Rtw",
      "name": "Acquired Podcast",
      "handle": "@AcquiredFM",
      "genre": "Technology & AI",
      "target_episodes": 10,
      "notes": "Long deep-dives on company histories"
    },
    {
      "channel_id": "UC9cn0TuPq4dnbTY-CBsm8XA",
      "name": "a16z Podcast",
      "handle": "@a16z",
      "genre": "Technology & AI",
      "target_episodes": 10,
      "notes": "Varied formats, shorter episodes"
    },
    {
      "channel_id": "UCZcR2SVWaGWNlMqPxvQS3vw",
      "name": "Hard Fork (NYT)",
      "handle": "@hardfork",
      "genre": "Technology & AI",
      "target_episodes": 10,
      "notes": "Mainstream tech journalism perspective"
    },
    {
      "channel_id": "UCjNRVMBVI30Sak_p6HRWhIA",
      "name": "The Cognitive Revolution",
      "handle": "@CognitiveRevolutionPodcast",
      "genre": "Technology & AI",
      "target_episodes": 10,
      "notes": "Niche but highly knowledge-dense AI discussions"
    },
    {
      "channel_id": "UCznv7Vf9nBdJYvBagFdAHWw",
      "name": "The Tim Ferriss Show",
      "handle": "@timferriss",
      "genre": "Business & Entrepreneurship",
      "target_episodes": 10,
      "notes": "Long-form with world-class performers"
    },
    {
      "channel_id": "UCyaN6mg5u8Cjy2ZI4ikWaug",
      "name": "My First Million",
      "handle": "@MyFirstMillionPod",
      "genre": "Business & Entrepreneurship",
      "target_episodes": 10,
      "notes": "Business ideas, trend analysis"
    },
    {
      "channel_id": "UC6t1O76G0jYXOAoYCm153dA",
      "name": "Lenny's Podcast",
      "handle": "@LennysPodcast",
      "genre": "Business & Entrepreneurship",
      "target_episodes": 10,
      "notes": "Product management focused"
    },
    {
      "channel_id": "UCcefcZRL2oaA_uBNeo5UOWg",
      "name": "Y Combinator",
      "handle": "@ycombinator",
      "genre": "Business & Entrepreneurship",
      "target_episodes": 10,
      "notes": "Startup advice from top accelerator"
    },
    {
      "channel_id": "UCLtTf_uKt0Itd0NG7txrwXA",
      "name": "The Knowledge Project",
      "handle": "@tkppodcast",
      "genre": "Business & Entrepreneurship",
      "target_episodes": 10,
      "notes": "Mental models, decision making"
    },
    {
      "channel_id": "UC2D2CMWXMOVWx7giW1n3LIg",
      "name": "Huberman Lab",
      "handle": "@hubermanlab",
      "genre": "Science & Health",
      "target_episodes": 10,
      "notes": "Long episodes (2-3 hrs) — great chunking test"
    },
    {
      "channel_id": "UC8kGsMa0LygSX9nkBcBH1Sg",
      "name": "The Peter Attia Drive",
      "handle": "@PeterAttiaMD",
      "genre": "Science & Health",
      "target_episodes": 10,
      "notes": "Deep medical/scientific discussions"
    },
    {
      "channel_id": "UCWF8SqJVNlx-ctXbLswcTcA",
      "name": "FoundMyFitness",
      "handle": "@FoundMyFitness",
      "genre": "Science & Health",
      "target_episodes": 10,
      "notes": "Nutrition, genetics, aging research"
    },
    {
      "channel_id": "UCqoAEDirJPjEUFcF2FklnBA",
      "name": "StarTalk",
      "handle": "@StarTalk",
      "genre": "Science & Health",
      "target_episodes": 10,
      "notes": "Science + comedy, broad appeal"
    },
    {
      "channel_id": "UCnYMOamNKLGVlJgRUbamveA",
      "name": "Impact Theory",
      "handle": "@TomBilyeu",
      "genre": "Education & Self-Improvement",
      "target_episodes": 10,
      "notes": "Mindset, entrepreneurship, personal growth"
    },
    {
      "channel_id": "UCoOae5nYA7VqaXzerajD0lg",
      "name": "Deep Dive with Ali Abdaal",
      "handle": "@aliabdaal",
      "genre": "Education & Self-Improvement",
      "target_episodes": 10,
      "notes": "Productivity, learning, life design"
    },
    {
      "channel_id": "UCGq-a57w-aPwyi3pW7XLiHw",
      "name": "The Diary of a CEO",
      "handle": "@TheDiaryOfACEO",
      "genre": "Education & Self-Improvement",
      "target_episodes": 10,
      "notes": "Fastest-growing podcast, diverse topics"
    },
    {
      "channel_id": "UCQ-rrUCsJLNjFdPtKq0YOfA",
      "name": "Founders Podcast",
      "handle": "@founderspodcast1",
      "genre": "Education & Self-Improvement",
      "target_episodes": 10,
      "notes": "Solo deep-dives on founder bios — clean transcripts"
    },
    {
      "channel_id": "UCIaH-gZIVC432YRjNVvnyCA",
      "name": "Modern Wisdom",
      "handle": "@ChrisWillx",
      "genre": "Education & Self-Improvement",
      "target_episodes": 10,
      "notes": "Psychology, fitness, philosophy"
    },
    {
      "channel_id": "UCf0PBRjhf0rF8fWBIxTuoWA",
      "name": "20VC with Harry Stebbings",
      "handle": "@20VC",
      "genre": "Startup & VC Focused",
      "target_episodes": 10,
      "notes": "Short episodes, high signal VC/founder interviews"
    },
    {
      "channel_id": "UCiemDAS1bXMBTx3jIIOukFg",
      "name": "Masters of Scale",
      "handle": "@MastersofScale_",
      "genre": "Startup & VC Focused",
      "target_episodes": 10,
      "notes": "Narrative interviews on scaling companies"
    },
    {
      "channel_id": "UCzQUP1qoWDoEbmsQxvdjxgQ",
      "name": "Joe Rogan Experience",
      "handle": "@joerogan",
      "genre": "Cross-Disciplinary",
      "target_episodes": 10,
      "notes": "Cherry-pick tech/science/business guests ONLY"
    },
    {
      "channel_id": "UCwcWc2zH0m66_CHILH1seNg",
      "name": "Wondery (How I Built This)",
      "handle": "@WonderyMedia",
      "genre": "Business & Entrepreneurship",
      "target_episodes": 10,
      "notes": "Features 'How I Built This' episodes"
    }
  ]
}